django_json_widget/__init__.py
django_json_widget/apps.py
django_json_widget/models.py
django_json_widget/urls.py
django_json_widget/views.py
django_json_widget/widgets.py
django_json_widget/static/css/django_json_widget.css
django_json_widget/static/dist/jsoneditor.min.css
django_json_widget/static/dist/jsoneditor.min.js
django_json_widget/static/dist/img/jsoneditor-icons.svg
django_json_widget/templates/django_json_widget.html
django_json_widget-2.1.1.dist-info/licenses/AUTHORS.rst
django_json_widget-2.1.1.dist-info/licenses/LICENSE
django_json_widget-2.1.1.dist-info/METADATA
django_json_widget-2.1.1.dist-info/WHEEL
django_json_widget-2.1.1.dist-info/top_level.txt
django_json_widget-2.1.1.dist-info/RECORD
